ambition_reports/__init__.py
ambition_reports/ae_report.py
ambition_reports/apps.py
ambition_reports/death_report.py
ambition_reports/pdf_report.py
ambition_reports/tests/__init__.py
ambition_reports/tests/urls.py
ambition_reports/tests/tests/__init__.py
ambition_reports/tests/tests/test_reports.py
ambition_reports-0.1.11.dist-info/LICENSE
ambition_reports-0.1.11.dist-info/METADATA
ambition_reports-0.1.11.dist-info/WHEEL
ambition_reports-0.1.11.dist-info/top_level.txt
ambition_reports-0.1.11.dist-info/RECORD
