Metadata-Version: 2.1
Name: ambition-reports
Version: 0.1.11
Summary: PDF reports for ambition.
Home-page: https://github.com/ambition-trialtrial/ambition-reports
Author: Erik van Widenfelt
Author-email: ew2789@gmail.com
License: GPL license, see LICENSE
Keywords: django ambition PDF reports
Platform: UNKNOWN
Classifier: Environment :: Web Environment
Classifier: Framework :: Django
Classifier: Intended Audience :: Developers
Classifier: Intended Audience :: Science/Research
Classifier: License :: OSI Approved :: GNU General Public License v3 (GPLv3)
Classifier: Operating System :: OS Independent
Classifier: Programming Language :: Python :: 3.7
Classifier: Topic :: Internet :: WWW/HTTP
Classifier: Topic :: Internet :: WWW/HTTP :: Dynamic Content
Requires-Python: >=3.7
Requires-Dist: ambition-ae
Requires-Dist: ambition-prn
Requires-Dist: edc-constants
Requires-Dist: edc-reports
Requires-Dist: inflect
Requires-Dist: reportlab
